parcae/__init__.py
parcae/api.py
parcae/cli.py
parcae-0.1.1.data/data/models/hmm.npz
parcae-0.1.1.dist-info/licenses/LICENSE
parcae-0.1.1.dist-info/METADATA
parcae-0.1.1.dist-info/WHEEL
parcae-0.1.1.dist-info/entry_points.txt
parcae-0.1.1.dist-info/top_level.txt
parcae-0.1.1.dist-info/RECORD
