Metadata-Version: 2.4
Name: parcae
Version: 0.1.1
Summary: Infer daily rhythm and sleep schedule from message timestamps
Project-URL: Homepage, https://github.com/jeremyctrl/parcae
Project-URL: Repository, https://github.com/jeremyctrl/parcae
Project-URL: Issues, https://github.com/jeremyctrl/parcae/issues
Requires-Python: >=3.13
License-File: LICENSE
Requires-Dist: numpy>=2.4.1
Provides-Extra: train
Requires-Dist: hmmlearn>=0.3.3; extra == "train"
Requires-Dist: matplotlib>=3.10.8; extra == "train"
Requires-Dist: pandas>=3.0.0; extra == "train"
Dynamic: license-file
